fastworkflow/.DS_Store
fastworkflow/__init__.py
fastworkflow/_commands/.gitkeep
fastworkflow/_workflows/__init__.py
fastworkflow/_workflows/command_metadata_extraction/__init__.py
fastworkflow/_workflows/command_metadata_extraction/_commands/ErrorCorrection/abort.py
fastworkflow/_workflows/command_metadata_extraction/_commands/ErrorCorrection/you_misunderstood.py
fastworkflow/_workflows/command_metadata_extraction/_commands/IntentDetection/go_up.py
fastworkflow/_workflows/command_metadata_extraction/_commands/IntentDetection/reset_context.py
fastworkflow/_workflows/command_metadata_extraction/_commands/IntentDetection/what_can_i_do.py
fastworkflow/_workflows/command_metadata_extraction/_commands/IntentDetection/what_is_current_context.py
fastworkflow/_workflows/command_metadata_extraction/_commands/__init__.py
fastworkflow/_workflows/command_metadata_extraction/_commands/wildcard.py
fastworkflow/_workflows/command_metadata_extraction/command_context_model.json
fastworkflow/_workflows/command_metadata_extraction/intent_detection.py
fastworkflow/_workflows/command_metadata_extraction/parameter_extraction.py
fastworkflow/build/__main__.py
fastworkflow/build/ast_class_extractor.py
fastworkflow/build/class_analysis_structures.py
fastworkflow/build/cli_specification.md
fastworkflow/build/command_dependency_resolver.py
fastworkflow/build/command_file_generator.py
fastworkflow/build/command_file_template.py
fastworkflow/build/command_import_utils.py
fastworkflow/build/command_stub_generator.py
fastworkflow/build/context_folder_generator.py
fastworkflow/build/context_model_generator.py
fastworkflow/build/dependency_manager.py
fastworkflow/build/dir_scanner.py
fastworkflow/build/documentation_generator.py
fastworkflow/build/genai_postprocessor.py
fastworkflow/build/inheritance_block_regenerator.py
fastworkflow/build/libcst_transformers.py
fastworkflow/build/navigator_stub_generator.py
fastworkflow/build/pydantic_model_generator.py
fastworkflow/build/utterance_generator.py
fastworkflow-2.17.25.dist-info/LICENSE
fastworkflow-2.17.25.dist-info/METADATA
fastworkflow-2.17.25.dist-info/WHEEL
fastworkflow-2.17.25.dist-info/entry_points.txt
fastworkflow-2.17.25.dist-info/RECORD
