Metadata-Version: 2.1
Name: fastworkflow
Version: 2.17.25
Summary: A framework for rapidly building large-scale, deterministic, interactive workflows with a fault-tolerant, conversational UX
License: Apache-2.0
Keywords: fastworkflow,ai,workflow,llm,openai
Author: Dhar Rawal
Author-email: drawal@radiantlogic.com
Requires-Python: >=3.11,<3.14
Classifier: License :: OSI Approved :: Apache Software License
Classifier: Programming Language :: Python :: 3
Classifier: Programming Language :: Python :: 3.11
Classifier: Programming Language :: Python :: 3.12
Provides-Extra: fastapi
Provides-Extra: training
Requires-Dist: colorama (>=0.4.6,<0.5.0)
Requires-Dist: datasets (>=4.0.0,<5.0.0) ; extra == "training"
Requires-Dist: dspy (>=3.0.1,<4.0.0)
Requires-Dist: fastapi (>=0.120.1) ; extra == "fastapi"
Requires-Dist: fastapi-mcp (>=0.4.0,<0.5.0) ; extra == "fastapi"
Requires-Dist: libcst (>=1.8.2,<2.0.0)
Requires-Dist: litellm[proxy] (>=1.80.5,<2.0.0)
Requires-Dist: mmh3 (>=5.1.0,<6.0.0)
Requires-Dist: openai (>=2.8.0)
Requires-Dist: prompt_toolkit (>=3.0.43,<4.0.0)
Requires-Dist: pydantic (>=2.9.2,<3.0.0)
Requires-Dist: python-dotenv (>=1.0.1,<2.0.0)
Requires-Dist: python-jose[cryptography] (>=3.3.0,<4.0.0) ; extra == "fastapi"
Requires-Dist: python-levenshtein (>=0.27.1,<0.28.0)
Requires-Dist: scikit-learn (>=1.6.1,<2.0.0)
Requires-Dist: speedict (>=0.3.12,<0.4.0)
Requires-Dist: torch (>=2.7.1,<3.0.0)
Requires-Dist: transformers (>=4.48.2,<5.0.0)
Requires-Dist: uvicorn (>=0.31.1,<0.32.0) ; extra == "fastapi"
Project-URL: homepage, https://github.com/radiantlogicinc/fastworkflow
Project-URL: repository, https://github.com/radiantlogicinc/fastworkflow
